Metadata-Version: 2.1
Name: pandas-df-sql
Version: 0.11
Summary: Perform SQL queries on pandas dataframes
Home-page: UNKNOWN
Author: Leo Liu
Author-email: leo.liu@unsw.edu.au
License: UNKNOWN
Platform: UNKNOWN
License-File: LICENSE
